pykoplenti/__init__.py
pykoplenti/api.py
pykoplenti/cli.py
pykoplenti/extended.py
pykoplenti/model.py
pykoplenti/py.typed
pykoplenti-1.5.0.dist-info/METADATA
pykoplenti-1.5.0.dist-info/WHEEL
pykoplenti-1.5.0.dist-info/entry_points.txt
pykoplenti-1.5.0.dist-info/licenses/LICENSE
pykoplenti-1.5.0.dist-info/RECORD
