Metadata-Version: 2.4
Name: pykoplenti
Version: 1.5.0
Summary: Python REST-Client for Kostal Plenticore Solar Inverters
Project-URL: repository, https://github.com/stegm/pykoplenti
Project-URL: changelog, https://github.com/stegm/pykoplenti/blob/master/CHANGELOG.md
Project-URL: issues, https://github.com/stegm/pykoplenti/issues
Author: @stegm
License-Expression: Apache-2.0
License-File: LICENSE
Keywords: kostal,plenticore,rest,solar
Classifier: Development Status :: 4 - Beta
Classifier: Environment :: Console
Classifier: Intended Audience :: Developers
Classifier: License :: OSI Approved :: Apache Software License
Classifier: Programming Language :: Python :: 3
Classifier: Programming Language :: Python :: 3.9
Classifier: Programming Language :: Python :: 3.10
Classifier: Programming Language :: Python :: 3.11
Classifier: Programming Language :: Python :: 3.12
Classifier: Programming Language :: Python :: 3.13
Classifier: Topic :: Software Development :: Libraries
Requires-Python: >=3.9
Requires-Dist: aiohttp~=3.8
Requires-Dist: pycryptodome~=3.19
Requires-Dist: pydantic<3,>=1.10
Provides-Extra: cli
Requires-Dist: click>=8.0; extra == 'cli'
Requires-Dist: prompt-toolkit>=3.0; extra == 'cli'
